<?xml version="1.0"?>
<Informal_Settlement id="Informal Settlement" xmlns:ev="http://www.w3.org/2001/xml-events" xmlns:orx="http://openrosa.org/xforms" xmlns:jr="http://openrosa.org/javarosa" xmlns:h="http://www.w3.org/1999/xhtml" xmlns:xsd="http://www.w3.org/2001/XMLSchema">
	<in_person>
		<first_name>
			James
		</first_name>
		<middle_name>
			Njoguna
		</middle_name>
		<last_name>
			Mwangi
		</last_name>
		<national_id>
			26410623
		</national_id>
		<gender>
			M
		</gender>
		<date_of_birth>
			2013-09-26
		</date_of_birth>
		<marital_status>
			Single
		</marital_status>
		<telephone_number>
			91826282
		</telephone_number>
		<address>
			0110
		</address>
		<residence_area>
			Nairobi
		</residence_area>
		<household_relation>
			Son
		</household_relation>
		<Photo_supporting_document>
			1611312270072.jpg
		</Photo_supporting_document>
		<Identification-Card_supporting_document />
	</in_person>
	<in_structure>
		<code>
			001
		</code>
		<name>
			Main house
		</name>
		<ownership_type>
			Private Individual
		</ownership_type>
		<related_structures>
			Toilet Bathroom
		</related_structures>
		<recognition_status>
			No
		</recognition_status>
		<utilities>
			Electricity
		</utilities>
		<location>
			Mashimoni
		</location>
		<spatial_geometry>
			-1.2625275941471585 36.85714736580849 0.0 0.0;-1.2623442426217355 36.857082657516 0.0 0.0;-1.2623442426217355 36.857082657516 0.0 0.0;-1.2623442426217355 36.857082657516 0.0 0.0;-1.2623737397601544 36.857005544006824 0.0 0.0;-1.262551057778372 36.85706187039614 0.0 0.0;-1.2625275941471585 36.85714736580849 0.0 0.0;
		</spatial_geometry>
		<supporting_document>
			1611312445012.jpg
		</supporting_document>
	</in_structure>
	<social_tenure>
		<tenure_type>
			Owner
		</tenure_type>
		<validity_start />
		<validity_end />
		<tenure_share>
			100
		</tenure_share>
		<supporting_document />
	</social_tenure>
	<meta>
		<instanceID>
			uuid:40097509-70e4-4acd-844a-5a8ca2a5ea30
		</instanceID>
	</meta>
</Informal_Settlement>
